bear_config/__init__.py
bear_config/__main__.py
bear_config/common.py
bear_config/dir_manager.py
bear_config/manager.py
bear_config/py.typed
bear_config/toml_handler.py
bear_config/_internal/__init__.py
bear_config/_internal/_cmds.py
bear_config/_internal/_version.pyi
bear_config/_internal/cli.py
bear_config/_internal/debug.py
bear_config/_internal/info.py
bear_config-1.0.6.dist-info/METADATA
bear_config-1.0.6.dist-info/WHEEL
bear_config-1.0.6.dist-info/entry_points.txt
bear_config-1.0.6.dist-info/RECORD
