Metadata-Version: 2.4
Name: bear-config
Version: 1.0.6
Summary: A useful Pydantic based config system with various options
Author-email: chaz <bright.lid5647@fastmail.com>
Requires-Python: >=3.12
Requires-Dist: pydantic>=2.12.4
Requires-Dist: tomlkit>=0.14.0
